LICENSE
MANIFEST.in
README.md
requirements.txt
setup.py
vectordb/__init__.py
vectordb/__main__.py
vectordb.egg-info/PKG-INFO
vectordb.egg-info/SOURCES.txt
vectordb.egg-info/dependency_links.txt
vectordb.egg-info/entry_points.txt
vectordb.egg-info/requires.txt
vectordb.egg-info/top_level.txt
vectordb/client/__init__.py
vectordb/client/client.py
vectordb/db/__init__.py
vectordb/db/base.py
vectordb/db/hnsw_vectordb.py
vectordb/db/inmemory_exact_vectordb.py
vectordb/db/service.py
vectordb/db/executors/__init__.py
vectordb/db/executors/hnsw_indexer.py
vectordb/db/executors/inmemory_exact_indexer.py
vectordb/db/executors/typed_executor.py
vectordb/utils/__init__.py
vectordb/utils/create_doc_type.py
vectordb/utils/pass_parameters.py
vectordb/utils/push_to_hubble.py
vectordb/utils/sort_matches_by_score.py
vectordb/utils/unify_input_output.py